mwconv/__init__.py
mwconv/__main__.py
mwconv/attributes.py
mwconv/base.py
mwconv/table.py
mwconv/token_scanner.py
mwconv/wiki_parse.py
mwconv/wikilist.py
mwconv/writer/__init__.py
mwconv/writer/extensions.py
mwconv/writer/html_writer.py
mwconv/writer/md_safe_writer.py
mwconv/writer/md_writer.py
mwconv/writer/mw_writer.py
mwconv/writer/text_writer.py
mwconv-1.6.2.dist-info/LICENCE
mwconv-1.6.2.dist-info/METADATA
mwconv-1.6.2.dist-info/WHEEL
mwconv-1.6.2.dist-info/entry_points.txt
mwconv-1.6.2.dist-info/top_level.txt
mwconv-1.6.2.dist-info/RECORD
