Metadata-Version: 2.1
Name: mwconv
Version: 1.6.2
Summary: Wiki text convertions based on MediaWiki
Home-page: https://hg.sr.ht/~sratcliffe/mwconv
Author: Steve Ratcliffe
Author-email: steve@itinken.com
License: MIT
Platform: UNKNOWN
Classifier: Development Status :: 5 - Production/Stable
Classifier: Intended Audience :: Developers
Classifier: License :: OSI Approved :: MIT License
Classifier: Programming Language :: Python :: 2
Classifier: Programming Language :: Python :: 2.7
Classifier: Programming Language :: Python :: 3
Requires-Dist: six
Requires-Dist: pygments
